monadic_error/__init__.py
monadic_error/attempt.py
monadic_error/option.py
monadic_error/utils.py
monadic_error-3.0.2.dist-info/METADATA
monadic_error-3.0.2.dist-info/WHEEL
monadic_error-3.0.2.dist-info/RECORD
