Metadata-Version: 2.1
Name: monadic-error
Version: 3.0.2
Summary: Monads used for handling Errors. Contains Attempt and Option.
Author: Ian Kollipara
Author-email: ian.kollipara@cune.org
Requires-Python: >=3.12,<4.0
Classifier: Programming Language :: Python :: 3
Classifier: Programming Language :: Python :: 3.12
